amc/__init__.py
amc/__main__.py
amc/_util.py
amc/ast.py
amc/reduction.py
amc/output/__init__.py
amc/output/latex.py
amc/parser/__init__.py
amc/parser/_lextab.py
amc/parser/_parser.py
amc/parser/_parsetab.py
amc/parser/_ply/__init__.py
amc/parser/_ply/lex.py
amc/parser/_ply/yacc.py
amc/yutsis/__init__.py
amc/yutsis/_cg.py
amc/yutsis/_delta.py
amc/yutsis/_edge.py
amc/yutsis/_functions.py
amc/yutsis/_graph.py
amc/yutsis/_idx.py
amc/yutsis/_ninej.py
amc/yutsis/_node.py
amc/yutsis/_sixj.py
amc/yutsis/_threej.py
amc/yutsis/_threejm.py
amc/yutsis/_tridelta.py
amc/yutsis/_twelvej.py
amc-0.9.5.dist-info/LICENSE
amc-0.9.5.dist-info/METADATA
amc-0.9.5.dist-info/WHEEL
amc-0.9.5.dist-info/entry_points.txt
amc-0.9.5.dist-info/top_level.txt
amc-0.9.5.dist-info/RECORD
