Metadata-Version: 2.1
Name: amc
Version: 0.9.5
Summary: Automatic angular-momentum reduction
Home-page: https://github.com/radnut/amc
Author: Julien Ripoche, Alexander Tichai, Roland Wirth
License: UNKNOWN
Keywords: angular momentum,symbolic computation
Platform: UNKNOWN
Classifier: Development Status :: 5 - Production/Stable
Classifier: Environment :: Console
Classifier: Intended Audience :: Science/Research
Classifier: License :: OSI Approved :: GNU General Public License v3 or later (GPLv3+)
Classifier: Operating System :: OS Independent
Classifier: Programming Language :: Python :: 3 :: Only
Classifier: Topic :: Scientific/Engineering :: Chemistry
Classifier: Topic :: Scientific/Engineering :: Physics
Requires-Python: >=3
